{"id": "0h7jEUbD9K8", "title": "Ponta De Areia", "formats": [{"asr": 48000, "filesize": 2241359, "format_id": "249", "format_note": "tiny", "fps": null, "height": null, "quality": 0, "tbr": 53.251, "url": "https://rr5---sn-0opoxu-ihvr.googlevideo.com/videoplayback?expire=1670741341&ei=_SiVY_AZz4WSBsjlpOAL&ip=189.173.225.87&id=o-ALa5WPpq7c-P_Vg3e1gjJ6dLt9ajSiAMlpktUFlus7RO&itag=249&source=youtube&requiressl=yes&mh=or&mm=31%2C29&mn=sn-0opoxu-ihvr%2Csn-q4fl6nsr&ms=au%2Crdu&mv=m&mvi=5&pcm2cms=yes&pl=24&gcr=mx&initcwndbps=790000&vprv=1&mime=audio%2Fwebm&ns=vNF8sqv81lslM9vJtgRdEJAJ&gir=yes&clen=2241359&dur=336.721&lmt=1565912327964935&mt=1670719029&fvip=3&keepalive=yes&fexp=24001373%2C24007246&beids=24239132&c=WEB&txp=1311222&n=NnA-f9Fy3wBIFe1iM&sparams=expire%2Cei%2Cip%2Cid%2Citag%2Csource%2Crequiressl%2Cgcr%2Cvprv%2Cmime%2Cns%2Cgir%2Cclen%2Cdur%2Clmt&lsparams=mh%2Cmm%2Cmn%2Cms%2Cmv%2Cmvi%2Cpcm2cms%2Cpl%2Cinitcwndbps&lsig=AG3C_xAwRAIfQnyIY2hibUmxUyaIcPSKw_nObxHGTA5BAY49hkPN7QIhAIlMx_yfNtII2F48R4eF70gJ8uEmYKWGecnPgKXFgvw8&sig=AOq0QJ8wRQIgfXUekKqAH_XbcGOiPhcXDLZjmAMKZWU2muksyUhszXcCIQC3r_o28g23r4X8RldK7an0lKXgl0Nz2HtwOsTTCOgHwQ==", "width": null, "ext": "webm", "vcodec": "none", "acodec": "opus", "abr": 53.251, "downloader_options": {"http_chunk_size": 10485760}, "container": "webm_dash", "format": "249 - audio only (tiny)", "protocol": "https", "http_headers": {"User-Agent": "Mozilla/5.0 (Windows NT 10.0; Win64; x64) AppleWebKit/537.36 (KHTML, like Gecko) Chrome/69.0.3497.124 Safari/537.36", "Accept-Charset": "ISO-8859-1,utf-8;q=0.7,*;q=0.7", "Accept": "text/html,application/xhtml+xml,application/xml;q=0.9,*/*;q=0.8", "Accept-Encoding": "gzip, deflate", "Accept-Language": "en-us,en;q=0.5"}}, {"asr": 48000, "filesize": 2975371, "format_id": "250", "format_note": "tiny", "fps": null, "height": null, "quality": 0, "tbr": 70.69, "url": "https://rr5---sn-0opoxu-ihvr.googlevideo.com/videoplayback?expire=1670741341&ei=_SiVY_AZz4WSBsjlpOAL&ip=189.173.225.87&id=o-ALa5WPpq7c-P_Vg3e1gjJ6dLt9ajSiAMlpktUFlus7RO&itag=250&source=youtube&requiressl=yes&mh=or&mm=31%2C29&mn=sn-0opoxu-ihvr%2Csn-q4fl6nsr&ms=au%2Crdu&mv=m&mvi=5&pcm2cms=yes&pl=24&gcr=mx&initcwndbps=790000&vprv=1&mime=audio%2Fwebm&ns=vNF8sqv81lslM9vJtgRdEJAJ&gir=yes&clen=2975371&dur=336.721&lmt=1565912332173554&mt=1670719029&fvip=3&keepalive=yes&fexp=24001373%2C24007246&beids=24239132&c=WEB&txp=1311222&n=NnA-f9Fy3wBIFe1iM&sparams=expire%2Cei%2Cip%2Cid%2Citag%2Csource%2Crequiressl%2Cgcr%2Cvprv%2Cmime%2Cns%2Cgir%2Cclen%2Cdur%2Clmt&lsparams=mh%2Cmm%2Cmn%2Cms%2Cmv%2Cmvi%2Cpcm2cms%2Cpl%2Cinitcwndbps&lsig=AG3C_xAwRQIhAJekfUVSxCvosNDSgBni4SjzwzbF7LA3Z-p9IDnufWCYAiBxfUFPSTA_lAZsldsAjEIH0TpQ79TuQ_a8mxUMCVhOCg%3D%3D&sig=AOq0QJ8wRQIhAK5hD-UwPuPatpcjjiqT_a7vcFYcpCJU7MnHYvhiIGZJAiAoS3pwqOPIEr2298ETJAqinr6UVuXTGYeCqg1hzb3tQA==", "width": null, "ext": "webm", "vcodec": "none", "acodec": "opus", "abr": 70.69, "downloader_options": {"http_chunk_size": 10485760}, "container": "webm_dash", "format": "250 - audio only (tiny)", "protocol": "https", "http_headers": {"User-Agent": "Mozilla/5.0 (Windows NT 10.0; Win64; x64) AppleWebKit/537.36 (KHTML, like Gecko) Chrome/69.0.3497.124 Safari/537.36", "Accept-Charset": "ISO-8859-1,utf-8;q=0.7,*;q=0.7", "Accept": "text/html,application/xhtml+xml,application/xml;q=0.9,*/*;q=0.8", "Accept-Encoding": "gzip, deflate", "Accept-Language": "en-us,en;q=0.5"}}, {"asr": 44100, "filesize": 5452356, "format_id": "140", "format_note": "tiny", "fps": null, "height": null, "quality": 0, "tbr": 129.545, "url": "https://rr5---sn-0opoxu-ihvr.googlevideo.com/videoplayback?expire=1670741341&ei=_SiVY_AZz4WSBsjlpOAL&ip=189.173.225.87&id=o-ALa5WPpq7c-P_Vg3e1gjJ6dLt9ajSiAMlpktUFlus7RO&itag=140&source=youtube&requiressl=yes&mh=or&mm=31%2C29&mn=sn-0opoxu-ihvr%2Csn-q4fl6nsr&ms=au%2Crdu&mv=m&mvi=5&pcm2cms=yes&pl=24&gcr=mx&initcwndbps=790000&vprv=1&mime=audio%2Fmp4&ns=vNF8sqv81lslM9vJtgRdEJAJ&gir=yes&clen=5452356&dur=336.706&lmt=1565910615050469&mt=1670719029&fvip=3&keepalive=yes&fexp=24001373%2C24007246&beids=24239132&c=WEB&txp=1311222&n=NnA-f9Fy3wBIFe1iM&sparams=expire%2Cei%2Cip%2Cid%2Citag%2Csource%2Crequiressl%2Cgcr%2Cvprv%2Cmime%2Cns%2Cgir%2Cclen%2Cdur%2Clmt&lsparams=mh%2Cmm%2Cmn%2Cms%2Cmv%2Cmvi%2Cpcm2cms%2Cpl%2Cinitcwndbps&lsig=AG3C_xAwRQIhAN394wOvIJu4sooMAe2QAI-zGrk9v7VBt0qGFge-JWUyAiAJ8aJoop9NTZ7gYbQn9LPboeGNHH1uPW4uclFck3jBEg%3D%3D&sig=AOq0QJ8wRQIhAPMar5Hy5Ov7Z9VH7nvAQWcwedyAyE0KRSYGVMBjHtC1AiAKBp_cFXtNTtitQAXzf5NPAv_aY57eUPXcucRXP17Kug==", "width": null, "ext": "m4a", "vcodec": "none", "acodec": "mp4a.40.2", "abr": 129.545, "downloader_options": {"http_chunk_size": 10485760}, "container": "m4a_dash", "format": "140 - audio only (tiny)", "protocol": "https", "http_headers": {"User-Agent": "Mozilla/5.0 (Windows NT 10.0; Win64; x64) AppleWebKit/537.36 (KHTML, like Gecko) Chrome/69.0.3497.124 Safari/537.36", "Accept-Charset": "ISO-8859-1,utf-8;q=0.7,*;q=0.7", "Accept": "text/html,application/xhtml+xml,application/xml;q=0.9,*/*;q=0.8", "Accept-Encoding": "gzip, deflate", "Accept-Language": "en-us,en;q=0.5"}}, {"asr": 48000, "filesize": 5869641, "format_id": "251", "format_note": "tiny", "fps": null, "height": null, "quality": 0, "tbr": 139.454, "url": "https://rr5---sn-0opoxu-ihvr.googlevideo.com/videoplayback?expire=1670741341&ei=_SiVY_AZz4WSBsjlpOAL&ip=189.173.225.87&id=o-ALa5WPpq7c-P_Vg3e1gjJ6dLt9ajSiAMlpktUFlus7RO&itag=251&source=youtube&requiressl=yes&mh=or&mm=31%2C29&mn=sn-0opoxu-ihvr%2Csn-q4fl6nsr&ms=au%2Crdu&mv=m&mvi=5&pcm2cms=yes&pl=24&gcr=mx&initcwndbps=790000&vprv=1&mime=audio%2Fwebm&ns=vNF8sqv81lslM9vJtgRdEJAJ&gir=yes&clen=5869641&dur=336.721&lmt=1565912333483070&mt=1670719029&fvip=3&keepalive=yes&fexp=24001373%2C24007246&beids=24239132&c=WEB&txp=1311222&n=NnA-f9Fy3wBIFe1iM&sparams=expire%2Cei%2Cip%2Cid%2Citag%2Csource%2Crequiressl%2Cgcr%2Cvprv%2Cmime%2Cns%2Cgir%2Cclen%2Cdur%2Clmt&lsparams=mh%2Cmm%2Cmn%2Cms%2Cmv%2Cmvi%2Cpcm2cms%2Cpl%2Cinitcwndbps&lsig=AG3C_xAwRgIhAOM-F_GkktPKk-59XB-3WXygy801HsTQyhUx4bFQ-7W-AiEArT9UCiOdjZI4awtbSKcMbeqC-DcN20ndhacyDBvGbAg%3D&sig=AOq0QJ8wRAIgJGs0MEf1njYtxNoKLeJfrNOzQQGWLit1YyQh8ucvVscCICvYkGjUqitwmWQmDVoQofJr6yZofGfn-KPsvny4fMuY", "width": null, "ext": "webm", "vcodec": "none", "acodec": "opus", "abr": 139.454, "downloader_options": {"http_chunk_size": 10485760}, "container": "webm_dash", "format": "251 - audio only (tiny)", "protocol": "https", "http_headers": {"User-Agent": "Mozilla/5.0 (Windows NT 10.0; Win64; x64) AppleWebKit/537.36 (KHTML, like Gecko) Chrome/69.0.3497.124 Safari/537.36", "Accept-Charset": "ISO-8859-1,utf-8;q=0.7,*;q=0.7", "Accept": "text/html,application/xhtml+xml,application/xml;q=0.9,*/*;q=0.8", "Accept-Encoding": "gzip, deflate", "Accept-Language": "en-us,en;q=0.5"}}, {"asr": null, "filesize": 809364, "format_id": "278", "format_note": "144p", "fps": 25, "height": 144, "quality": 0, "tbr": 19.231, "url": "https://rr5---sn-0opoxu-ihvr.googlevideo.com/videoplayback?expire=1670741341&ei=_SiVY_AZz4WSBsjlpOAL&ip=189.173.225.87&id=o-ALa5WPpq7c-P_Vg3e1gjJ6dLt9ajSiAMlpktUFlus7RO&itag=278&aitags=133%2C134%2C135%2C136%2C137%2C160%2C242%2C243%2C244%2C247%2C248%2C278&source=youtube&requiressl=yes&mh=or&mm=31%2C29&mn=sn-0opoxu-ihvr%2Csn-q4fl6nsr&ms=au%2Crdu&mv=m&mvi=5&pcm2cms=yes&pl=24&gcr=mx&initcwndbps=790000&vprv=1&mime=video%2Fwebm&ns=vNF8sqv81lslM9vJtgRdEJAJ&gir=yes&clen=809364&dur=336.680&lmt=1565912537967826&mt=1670719029&fvip=3&keepalive=yes&fexp=24001373%2C24007246&beids=24239132&c=WEB&txp=1311222&n=NnA-f9Fy3wBIFe1iM&sparams=expire%2Cei%2Cip%2Cid%2Caitags%2Csource%2Crequiressl%2Cgcr%2Cvprv%2Cmime%2Cns%2Cgir%2Cclen%2Cdur%2Clmt&lsparams=mh%2Cmm%2Cmn%2Cms%2Cmv%2Cmvi%2Cpcm2cms%2Cpl%2Cinitcwndbps&lsig=AG3C_xAwRQIgXVH0pSAq-TmEhhNLJ5wbnvG1kWuObHzNDgc9hfwOUfcCIQCW3k6o6AxffpeBtIkYwCGRXdjpleyfmCnUx39m3dsrpg%3D%3D&sig=AOq0QJ8wRQIhAO4e_KSb8c_Ks0Yk4Qmv4FqRJkq3BWIO2a4V27yewnJNAiBSlXPRYdv__pnDXTgalALrXUvR7LrNYiPHjDPQ8aNoEg==", "width": 144, "ext": "webm", "vcodec": "vp9", "acodec": "none", "vbr": 19.231, "downloader_options": {"http_chunk_size": 10485760}, "container": "webm_dash", "format": "278 - 144x144 (144p)", "protocol": "https", "http_headers": {"User-Agent": "Mozilla/5.0 (Windows NT 10.0; Win64; x64) AppleWebKit/537.36 (KHTML, like Gecko) Chrome/69.0.3497.124 Safari/537.36", "Accept-Charset": "ISO-8859-1,utf-8;q=0.7,*;q=0.7", "Accept": "text/html,application/xhtml+xml,application/xml;q=0.9,*/*;q=0.8", "Accept-Encoding": "gzip, deflate", "Accept-Language": "en-us,en;q=0.5"}}, {"asr": null, "filesize": 1438957, "format_id": "160", "format_note": "144p", "fps": 25, "height": 144, "quality": 0, "tbr": 34.191, "url": "https://rr5---sn-0opoxu-ihvr.googlevideo.com/videoplayback?expire=1670741341&ei=_SiVY_AZz4WSBsjlpOAL&ip=189.173.225.87&id=o-ALa5WPpq7c-P_Vg3e1gjJ6dLt9ajSiAMlpktUFlus7RO&itag=160&aitags=133%2C134%2C135%2C136%2C137%2C160%2C242%2C243%2C244%2C247%2C248%2C278&source=youtube&requiressl=yes&mh=or&mm=31%2C29&mn=sn-0opoxu-ihvr%2Csn-q4fl6nsr&ms=au%2Crdu&mv=m&mvi=5&pcm2cms=yes&pl=24&gcr=mx&initcwndbps=790000&vprv=1&mime=video%2Fmp4&ns=vNF8sqv81lslM9vJtgRdEJAJ&gir=yes&clen=1438957&dur=336.680&lmt=1565910637075837&mt=1670719029&fvip=3&keepalive=yes&fexp=24001373%2C24007246&beids=24239132&c=WEB&txp=1311222&n=NnA-f9Fy3wBIFe1iM&sparams=expire%2Cei%2Cip%2Cid%2Caitags%2Csource%2Crequiressl%2Cgcr%2Cvprv%2Cmime%2Cns%2Cgir%2Cclen%2Cdur%2Clmt&lsparams=mh%2Cmm%2Cmn%2Cms%2Cmv%2Cmvi%2Cpcm2cms%2Cpl%2Cinitcwndbps&lsig=AG3C_xAwRgIhAIMSq9-245WMp9j3jK05rxdyysTss7E2QXIYcccXidvaAiEAzu7st1ud2ZRocxWpAEnnCiR-fyiq-QlOe3T5S0_vRLY%3D&sig=AOq0QJ8wRAIgFjuSBkMtViF58TWFwWauNn9fnkdAd5ti369NKJtFLDUCIEjUhGzW7IjWi6zWC8VmtPffWLLSfFlbuplvX2EJXXzC", "width": 144, "ext": "mp4", "vcodec": "avc1.4d400b", "acodec": "none", "vbr": 34.191, "downloader_options": {"http_chunk_size": 10485760}, "container": "mp4_dash", "format": "160 - 144x144 (144p)", "protocol": "https", "http_headers": {"User-Agent": "Mozilla/5.0 (Windows NT 10.0; Win64; x64) AppleWebKit/537.36 (KHTML, like Gecko) Chrome/69.0.3497.124 Safari/537.36", "Accept-Charset": "ISO-8859-1,utf-8;q=0.7,*;q=0.7", "Accept": "text/html,application/xhtml+xml,application/xml;q=0.9,*/*;q=0.8", "Accept-Encoding": "gzip, deflate", "Accept-Language": "en-us,en;q=0.5"}}, {"asr": null, "filesize": 1670171, "format_id": "242", "format_note": "240p", "fps": 25, "height": 240, "quality": 1, "tbr": 39.685, "url": "https://rr5---sn-0opoxu-ihvr.googlevideo.com/videoplayback?expire=1670741341&ei=_SiVY_AZz4WSBsjlpOAL&ip=189.173.225.87&id=o-ALa5WPpq7c-P_Vg3e1gjJ6dLt9ajSiAMlpktUFlus7RO&itag=242&aitags=133%2C134%2C135%2C136%2C137%2C160%2C242%2C243%2C244%2C247%2C248%2C278&source=youtube&requiressl=yes&mh=or&mm=31%2C29&mn=sn-0opoxu-ihvr%2Csn-q4fl6nsr&ms=au%2Crdu&mv=m&mvi=5&pcm2cms=yes&pl=24&gcr=mx&initcwndbps=790000&vprv=1&mime=video%2Fwebm&ns=vNF8sqv81lslM9vJtgRdEJAJ&gir=yes&clen=1670171&dur=336.680&lmt=1565912537987179&mt=1670719029&fvip=3&keepalive=yes&fexp=24001373%2C24007246&beids=24239132&c=WEB&txp=1311222&n=NnA-f9Fy3wBIFe1iM&sparams=expire%2Cei%2Cip%2Cid%2Caitags%2Csource%2Crequiressl%2Cgcr%2Cvprv%2Cmime%2Cns%2Cgir%2Cclen%2Cdur%2Clmt&lsparams=mh%2Cmm%2Cmn%2Cms%2Cmv%2Cmvi%2Cpcm2cms%2Cpl%2Cinitcwndbps&lsig=AG3C_xAwRAIgEMLObmDjs-0uzaIGCnFc1M4lw05fxBJuVRfJLU_2z3oCIF5Kmd3MEVzHM_xyfOiyvjVcTPQvvnaG-Ey3IvtMl2--&sig=AOq0QJ8wRgIhAJPAfgrf6LaXOsNREPIn_LzsKgMiD7sZC-omXoRyvcCwAiEAlv4EqEOKAPeX6dcKdesCuONY-9sSBIwShQe2sb30ioA=", "width": 240, "ext": "webm", "vcodec": "vp9", "acodec": "none", "vbr": 39.685, "downloader_options": {"http_chunk_size": 10485760}, "container": "webm_dash", "format": "242 - 240x240 (240p)", "protocol": "https", "http_headers": {"User-Agent": "Mozilla/5.0 (Windows NT 10.0; Win64; x64) AppleWebKit/537.36 (KHTML, like Gecko) Chrome/69.0.3497.124 Safari/537.36", "Accept-Charset": "ISO-8859-1,utf-8;q=0.7,*;q=0.7", "Accept": "text/html,application/xhtml+xml,application/xml;q=0.9,*/*;q=0.8", "Accept-Encoding": "gzip, deflate", "Accept-Language": "en-us,en;q=0.5"}}, {"asr": null, "filesize": 3358962, "format_id": "133", "format_note": "240p", "fps": 25, "height": 240, "quality": 1, "tbr": 79.813, "url": "https://rr5---sn-0opoxu-ihvr.googlevideo.com/videoplayback?expire=1670741341&ei=_SiVY_AZz4WSBsjlpOAL&ip=189.173.225.87&id=o-ALa5WPpq7c-P_Vg3e1gjJ6dLt9ajSiAMlpktUFlus7RO&itag=133&aitags=133%2C134%2C135%2C136%2C137%2C160%2C242%2C243%2C244%2C247%2C248%2C278&source=youtube&requiressl=yes&mh=or&mm=31%2C29&mn=sn-0opoxu-ihvr%2Csn-q4fl6nsr&ms=au%2Crdu&mv=m&mvi=5&pcm2cms=yes&pl=24&gcr=mx&initcwndbps=790000&vprv=1&mime=video%2Fmp4&ns=vNF8sqv81lslM9vJtgRdEJAJ&gir=yes&clen=3358962&dur=336.680&lmt=1565910640770495&mt=1670719029&fvip=3&keepalive=yes&fexp=24001373%2C24007246&beids=24239132&c=WEB&txp=1311222&n=NnA-f9Fy3wBIFe1iM&sparams=expire%2Cei%2Cip%2Cid%2Caitags%2Csource%2Crequiressl%2Cgcr%2Cvprv%2Cmime%2Cns%2Cgir%2Cclen%2Cdur%2Clmt&lsparams=mh%2Cmm%2Cmn%2Cms%2Cmv%2Cmvi%2Cpcm2cms%2Cpl%2Cinitcwndbps&lsig=AG3C_xAwRQIgV3WomruENVn7H3JXNid4grNiccXQ2OFdnQuP_pDBKV4CIQDReECdOFvUuehEs3RJurEpBj_s4llEk5AoxyGOYKoNjg%3D%3D&sig=AOq0QJ8wRQIgQylALFYotBlGMqwWOocME4dCEZINmWX9O0cToMyhhr4CIQCFD5PE4QwZTTG--jyjLf41v89S45C6Ry9dklfg_rZI9A==", "width": 240, "ext": "mp4", "vcodec": "avc1.4d400c", "acodec": "none", "vbr": 79.813, "downloader_options": {"http_chunk_size": 10485760}, "container": "mp4_dash", "format": "133 - 240x240 (240p)", "protocol": "https", "http_headers": {"User-Agent": "Mozilla/5.0 (Windows NT 10.0; Win64; x64) AppleWebKit/537.36 (KHTML, like Gecko) Chrome/69.0.3497.124 Safari/537.36", "Accept-Charset": "ISO-8859-1,utf-8;q=0.7,*;q=0.7", "Accept": "text/html,application/xhtml+xml,application/xml;q=0.9,*/*;q=0.8", "Accept-Encoding": "gzip, deflate", "Accept-Language": "en-us,en;q=0.5"}}, {"asr": null, "filesize": 1536950, "format_id": "134", "format_note": "360p", "fps": 25, "height": 360, "quality": 2, "tbr": 36.52, "url": "https://rr5---sn-0opoxu-ihvr.googlevideo.com/videoplayback?expire=1670741341&ei=_SiVY_AZz4WSBsjlpOAL&ip=189.173.225.87&id=o-ALa5WPpq7c-P_Vg3e1gjJ6dLt9ajSiAMlpktUFlus7RO&itag=134&aitags=133%2C134%2C135%2C136%2C137%2C160%2C242%2C243%2C244%2C247%2C248%2C278&source=youtube&requiressl=yes&mh=or&mm=31%2C29&mn=sn-0opoxu-ihvr%2Csn-q4fl6nsr&ms=au%2Crdu&mv=m&mvi=5&pcm2cms=yes&pl=24&gcr=mx&initcwndbps=790000&vprv=1&mime=video%2Fmp4&ns=vNF8sqv81lslM9vJtgRdEJAJ&gir=yes&clen=1536950&dur=336.680&lmt=1565910662140049&mt=1670719029&fvip=3&keepalive=yes&fexp=24001373%2C24007246&beids=24239132&c=WEB&txp=1311222&n=NnA-f9Fy3wBIFe1iM&sparams=expire%2Cei%2Cip%2Cid%2Caitags%2Csource%2Crequiressl%2Cgcr%2Cvprv%2Cmime%2Cns%2Cgir%2Cclen%2Cdur%2Clmt&lsparams=mh%2Cmm%2Cmn%2Cms%2Cmv%2Cmvi%2Cpcm2cms%2Cpl%2Cinitcwndbps&lsig=AG3C_xAwRQIhAPrpQjndAeUZLh2h64cwjwrrvJz311vSULosod6GEvflAiBwJnlZFO8v3EfU6Zgyd-rP1xk5MwWpz0XXt1FZeHRwCQ%3D%3D&sig=AOq0QJ8wRAIgWfPXkM_1y0WosPSYtCZr0hHuvpnccT11TIWVCb9ATW8CIBh9JGxuAob43ZsgW6z3at0iaXs2t4uznFJ06lAVvpD3", "width": 360, "ext": "mp4", "vcodec": "avc1.4d4015", "acodec": "none", "vbr": 36.52, "downloader_options": {"http_chunk_size": 10485760}, "container": "mp4_dash", "format": "134 - 360x360 (360p)", "protocol": "https", "http_headers": {"User-Agent": "Mozilla/5.0 (Windows NT 10.0; Win64; x64) AppleWebKit/537.36 (KHTML, like Gecko) Chrome/69.0.3497.124 Safari/537.36", "Accept-Charset": "ISO-8859-1,utf-8;q=0.7,*;q=0.7", "Accept": "text/html,application/xhtml+xml,application/xml;q=0.9,*/*;q=0.8", "Accept-Encoding": "gzip, deflate", "Accept-Language": "en-us,en;q=0.5"}}, {"asr": null, "filesize": 2894760, "format_id": "243", "format_note": "360p", "fps": 25, "height": 360, "quality": 2, "tbr": 68.783, "url": "https://rr5---sn-0opoxu-ihvr.googlevideo.com/videoplayback?expire=1670741341&ei=_SiVY_AZz4WSBsjlpOAL&ip=189.173.225.87&id=o-ALa5WPpq7c-P_Vg3e1gjJ6dLt9ajSiAMlpktUFlus7RO&itag=243&aitags=133%2C134%2C135%2C136%2C137%2C160%2C242%2C243%2C244%2C247%2C248%2C278&source=youtube&requiressl=yes&mh=or&mm=31%2C29&mn=sn-0opoxu-ihvr%2Csn-q4fl6nsr&ms=au%2Crdu&mv=m&mvi=5&pcm2cms=yes&pl=24&gcr=mx&initcwndbps=790000&vprv=1&mime=video%2Fwebm&ns=vNF8sqv81lslM9vJtgRdEJAJ&gir=yes&clen=2894760&dur=336.680&lmt=1565912537983920&mt=1670719029&fvip=3&keepalive=yes&fexp=24001373%2C24007246&beids=24239132&c=WEB&txp=1311222&n=NnA-f9Fy3wBIFe1iM&sparams=expire%2Cei%2Cip%2Cid%2Caitags%2Csource%2Crequiressl%2Cgcr%2Cvprv%2Cmime%2Cns%2Cgir%2Cclen%2Cdur%2Clmt&lsparams=mh%2Cmm%2Cmn%2Cms%2Cmv%2Cmvi%2Cpcm2cms%2Cpl%2Cinitcwndbps&lsig=AG3C_xAwRAIgRQ8-Vj8pdXs2jSwwHjPOLSI8IbgDsDdLR5fNMUDElrcCICuDT1skmdAj5XwV84fCZPPoe062WBcMbnBG8pKwjG2x&sig=AOq0QJ8wRQIgVRh_rkcVr7PsaGRyhe0BsAeMD10kV3AoJjUIy_9RwhYCIQCXlyfUehItsMRdda4bkS-X9lecTQpRVwax6n7iEWJNSw==", "width": 360, "ext": "webm", "vcodec": "vp9", "acodec": "none", "vbr": 68.783, "downloader_options": {"http_chunk_size": 10485760}, "container": "webm_dash", "format": "243 - 360x360 (360p)", "protocol": "https", "http_headers": {"User-Agent": "Mozilla/5.0 (Windows NT 10.0; Win64; x64) AppleWebKit/537.36 (KHTML, like Gecko) Chrome/69.0.3497.124 Safari/537.36", "Accept-Charset": "ISO-8859-1,utf-8;q=0.7,*;q=0.7", "Accept": "text/html,application/xhtml+xml,application/xml;q=0.9,*/*;q=0.8", "Accept-Encoding": "gzip, deflate", "Accept-Language": "en-us,en;q=0.5"}}, {"asr": null, "filesize": 2807619, "format_id": "135", "format_note": "480p", "fps": 25, "height": 480, "quality": 3, "tbr": 66.713, "url": "https://rr5---sn-0opoxu-ihvr.googlevideo.com/videoplayback?expire=1670741341&ei=_SiVY_AZz4WSBsjlpOAL&ip=189.173.225.87&id=o-ALa5WPpq7c-P_Vg3e1gjJ6dLt9ajSiAMlpktUFlus7RO&itag=135&aitags=133%2C134%2C135%2C136%2C137%2C160%2C242%2C243%2C244%2C247%2C248%2C278&source=youtube&requiressl=yes&mh=or&mm=31%2C29&mn=sn-0opoxu-ihvr%2Csn-q4fl6nsr&ms=au%2Crdu&mv=m&mvi=5&pcm2cms=yes&pl=24&gcr=mx&initcwndbps=790000&vprv=1&mime=video%2Fmp4&ns=vNF8sqv81lslM9vJtgRdEJAJ&gir=yes&clen=2807619&dur=336.680&lmt=1565910648715489&mt=1670719029&fvip=3&keepalive=yes&fexp=24001373%2C24007246&beids=24239132&c=WEB&txp=1311222&n=NnA-f9Fy3wBIFe1iM&sparams=expire%2Cei%2Cip%2Cid%2Caitags%2Csource%2Crequiressl%2Cgcr%2Cvprv%2Cmime%2Cns%2Cgir%2Cclen%2Cdur%2Clmt&lsparams=mh%2Cmm%2Cmn%2Cms%2Cmv%2Cmvi%2Cpcm2cms%2Cpl%2Cinitcwndbps&lsig=AG3C_xAwRQIgZ9yD4KahsrZqP0mYaUGhlsQtT_URLtnaFm2xPjtEJXwCIQCx6cwjfphvCql3QSxaa4VR1zgR6flV_BTISVX94dNHuw%3D%3D&sig=AOq0QJ8wRQIhAO6GDnl5Xj1j5qot1hIFC1yNhmnxnv9T3YtX2tKD97DkAiACt11Y4MJQzomsJDLD-xZAJrpkGB-boJn9ow8aO_Z2Hw==", "width": 480, "ext": "mp4", "vcodec": "avc1.4d401e", "acodec": "none", "vbr": 66.713, "downloader_options": {"http_chunk_size": 10485760}, "container": "mp4_dash", "format": "135 - 480x480 (480p)", "protocol": "https", "http_headers": {"User-Agent": "Mozilla/5.0 (Windows NT 10.0; Win64; x64) AppleWebKit/537.36 (KHTML, like Gecko) Chrome/69.0.3497.124 Safari/537.36", "Accept-Charset": "ISO-8859-1,utf-8;q=0.7,*;q=0.7", "Accept": "text/html,application/xhtml+xml,application/xml;q=0.9,*/*;q=0.8", "Accept-Encoding": "gzip, deflate", "Accept-Language": "en-us,en;q=0.5"}}, {"asr": null, "filesize": 5269927, "format_id": "244", "format_note": "480p", "fps": 25, "height": 480, "quality": 3, "tbr": 125.221, "url": "https://rr5---sn-0opoxu-ihvr.googlevideo.com/videoplayback?expire=1670741341&ei=_SiVY_AZz4WSBsjlpOAL&ip=189.173.225.87&id=o-ALa5WPpq7c-P_Vg3e1gjJ6dLt9ajSiAMlpktUFlus7RO&itag=244&aitags=133%2C134%2C135%2C136%2C137%2C160%2C242%2C243%2C244%2C247%2C248%2C278&source=youtube&requiressl=yes&mh=or&mm=31%2C29&mn=sn-0opoxu-ihvr%2Csn-q4fl6nsr&ms=au%2Crdu&mv=m&mvi=5&pcm2cms=yes&pl=24&gcr=mx&initcwndbps=790000&vprv=1&mime=video%2Fwebm&ns=vNF8sqv81lslM9vJtgRdEJAJ&gir=yes&clen=5269927&dur=336.680&lmt=1565912538079565&mt=1670719029&fvip=3&keepalive=yes&fexp=24001373%2C24007246&beids=24239132&c=WEB&txp=1311222&n=NnA-f9Fy3wBIFe1iM&sparams=expire%2Cei%2Cip%2Cid%2Caitags%2Csource%2Crequiressl%2Cgcr%2Cvprv%2Cmime%2Cns%2Cgir%2Cclen%2Cdur%2Clmt&lsparams=mh%2Cmm%2Cmn%2Cms%2Cmv%2Cmvi%2Cpcm2cms%2Cpl%2Cinitcwndbps&lsig=AG3C_xAwRgIhAPHExSepGEyKZMSXYphjn2JDzfz2imLLYw4R0MCnBx6ZAiEA5O3nFY4hwe-Vp7KQxVOzQsVXXPQU3_SWCL0NiVmdiYI%3D&sig=AOq0QJ8wRgIhAJcagxsFZN6F5-0zvcYJCuLNl0NkYb2XLLCz9sdp1v-9AiEA4Fa6BI1iuI-dNJBjSEx_jSeCXBwaC6_f3aUwJPvi-hQ=", "width": 480, "ext": "webm", "vcodec": "vp9", "acodec": "none", "vbr": 125.221, "downloader_options": {"http_chunk_size": 10485760}, "container": "webm_dash", "format": "244 - 480x480 (480p)", "protocol": "https", "http_headers": {"User-Agent": "Mozilla/5.0 (Windows NT 10.0; Win64; x64) AppleWebKit/537.36 (KHTML, like Gecko) Chrome/69.0.3497.124 Safari/537.36", "Accept-Charset": "ISO-8859-1,utf-8;q=0.7,*;q=0.7", "Accept": "text/html,application/xhtml+xml,application/xml;q=0.9,*/*;q=0.8", "Accept-Encoding": "gzip, deflate", "Accept-Language": "en-us,en;q=0.5"}}, {"asr": null, "filesize": 5371253, "format_id": "136", "format_note": "720p", "fps": 25, "height": 720, "quality": 4, "tbr": 127.628, "url": "https://rr5---sn-0opoxu-ihvr.googlevideo.com/videoplayback?expire=1670741341&ei=_SiVY_AZz4WSBsjlpOAL&ip=189.173.225.87&id=o-ALa5WPpq7c-P_Vg3e1gjJ6dLt9ajSiAMlpktUFlus7RO&itag=136&aitags=133%2C134%2C135%2C136%2C137%2C160%2C242%2C243%2C244%2C247%2C248%2C278&source=youtube&requiressl=yes&mh=or&mm=31%2C29&mn=sn-0opoxu-ihvr%2Csn-q4fl6nsr&ms=au%2Crdu&mv=m&mvi=5&pcm2cms=yes&pl=24&gcr=mx&initcwndbps=790000&vprv=1&mime=video%2Fmp4&ns=vNF8sqv81lslM9vJtgRdEJAJ&gir=yes&clen=5371253&dur=336.680&lmt=1565910637091432&mt=1670719029&fvip=3&keepalive=yes&fexp=24001373%2C24007246&beids=24239132&c=WEB&txp=1311222&n=NnA-f9Fy3wBIFe1iM&sparams=expire%2Cei%2Cip%2Cid%2Caitags%2Csource%2Crequiressl%2Cgcr%2Cvprv%2Cmime%2Cns%2Cgir%2Cclen%2Cdur%2Clmt&lsparams=mh%2Cmm%2Cmn%2Cms%2Cmv%2Cmvi%2Cpcm2cms%2Cpl%2Cinitcwndbps&lsig=AG3C_xAwRgIhAPVBxY7TjLV-YO6bBBNoMadZWrb6CU1FDD_NXk0hTbJnAiEA6p5-e0RnhRapqNVsH-rOvehfGDnXTS-HMPVlKEzIu08%3D&sig=AOq0QJ8wRAIgC3mPFkcFv_XNlyqiUsyMdNUUoX31leqchNvnhJEJQCACIG_AEb6oorYLp1uTBGmRckDHA2XCM7k6bTvZNix_4X-c", "width": 720, "ext": "mp4", "vcodec": "avc1.4d401f", "acodec": "none", "vbr": 127.628, "downloader_options": {"http_chunk_size": 10485760}, "container": "mp4_dash", "format": "136 - 720x720 (720p)", "protocol": "https", "http_headers": {"User-Agent": "Mozilla/5.0 (Windows NT 10.0; Win64; x64) AppleWebKit/537.36 (KHTML, like Gecko) Chrome/69.0.3497.124 Safari/537.36", "Accept-Charset": "ISO-8859-1,utf-8;q=0.7,*;q=0.7", "Accept": "text/html,application/xhtml+xml,application/xml;q=0.9,*/*;q=0.8", "Accept-Encoding": "gzip, deflate", "Accept-Language": "en-us,en;q=0.5"}}, {"asr": null, "filesize": 11005700, "format_id": "247", "format_note": "720p", "fps": 25, "height": 720, "quality": 4, "tbr": 261.511, "url": "https://rr5---sn-0opoxu-ihvr.googlevideo.com/videoplayback?expire=1670741341&ei=_SiVY_AZz4WSBsjlpOAL&ip=189.173.225.87&id=o-ALa5WPpq7c-P_Vg3e1gjJ6dLt9ajSiAMlpktUFlus7RO&itag=247&aitags=133%2C134%2C135%2C136%2C137%2C160%2C242%2C243%2C244%2C247%2C248%2C278&source=youtube&requiressl=yes&mh=or&mm=31%2C29&mn=sn-0opoxu-ihvr%2Csn-q4fl6nsr&ms=au%2Crdu&mv=m&mvi=5&pcm2cms=yes&pl=24&gcr=mx&initcwndbps=790000&vprv=1&mime=video%2Fwebm&ns=vNF8sqv81lslM9vJtgRdEJAJ&gir=yes&clen=11005700&dur=336.680&lmt=1565912537985980&mt=1670719029&fvip=3&keepalive=yes&fexp=24001373%2C24007246&beids=24239132&c=WEB&txp=1311222&n=NnA-f9Fy3wBIFe1iM&sparams=expire%2Cei%2Cip%2Cid%2Caitags%2Csource%2Crequiressl%2Cgcr%2Cvprv%2Cmime%2Cns%2Cgir%2Cclen%2Cdur%2Clmt&lsparams=mh%2Cmm%2Cmn%2Cms%2Cmv%2Cmvi%2Cpcm2cms%2Cpl%2Cinitcwndbps&lsig=AG3C_xAwRQIhAPeH9OEDuBqLYE7FHERgM8dc2686Im-YYBN5X3YJRd54AiBNQV_Vo9tFozSb95DTY4nPNp9AaJqbC04eWMWmW7FYGw%3D%3D&sig=AOq0QJ8wRgIhAMfyjkbKR-V_JofqpPldcfW3RZcp0M_ZOSYQyHbiVD3bAiEA3tvs6rzdPNR655i-kc__n5355BuqUcDPOaUGcG_t3ws=", "width": 720, "ext": "webm", "vcodec": "vp9", "acodec": "none", "vbr": 261.511, "downloader_options": {"http_chunk_size": 10485760}, "container": "webm_dash", "format": "247 - 720x720 (720p)", "protocol": "https", "http_headers": {"User-Agent": "Mozilla/5.0 (Windows NT 10.0; Win64; x64) AppleWebKit/537.36 (KHTML, like Gecko) Chrome/69.0.3497.124 Safari/537.36", "Accept-Charset": "ISO-8859-1,utf-8;q=0.7,*;q=0.7", "Accept": "text/html,application/xhtml+xml,application/xml;q=0.9,*/*;q=0.8", "Accept-Encoding": "gzip, deflate", "Accept-Language": "en-us,en;q=0.5"}}, {"asr": null, "filesize": 10162678, "format_id": "137", "format_note": "1080p", "fps": 25, "height": 1080, "quality": 5, "tbr": 241.479, "url": "https://rr5---sn-0opoxu-ihvr.googlevideo.com/videoplayback?expire=1670741341&ei=_SiVY_AZz4WSBsjlpOAL&ip=189.173.225.87&id=o-ALa5WPpq7c-P_Vg3e1gjJ6dLt9ajSiAMlpktUFlus7RO&itag=137&aitags=133%2C134%2C135%2C136%2C137%2C160%2C242%2C243%2C244%2C247%2C248%2C278&source=youtube&requiressl=yes&mh=or&mm=31%2C29&mn=sn-0opoxu-ihvr%2Csn-q4fl6nsr&ms=au%2Crdu&mv=m&mvi=5&pcm2cms=yes&pl=24&gcr=mx&initcwndbps=790000&vprv=1&mime=video%2Fmp4&ns=vNF8sqv81lslM9vJtgRdEJAJ&gir=yes&clen=10162678&dur=336.680&lmt=1565910649164424&mt=1670719029&fvip=3&keepalive=yes&fexp=24001373%2C24007246&beids=24239132&c=WEB&txp=1311222&n=NnA-f9Fy3wBIFe1iM&sparams=expire%2Cei%2Cip%2Cid%2Caitags%2Csource%2Crequiressl%2Cgcr%2Cvprv%2Cmime%2Cns%2Cgir%2Cclen%2Cdur%2Clmt&lsparams=mh%2Cmm%2Cmn%2Cms%2Cmv%2Cmvi%2Cpcm2cms%2Cpl%2Cinitcwndbps&lsig=AG3C_xAwRQIhAK_iI8eCIQHNYhLJJzWnxHH4VttU7OXhsTPR5PgxaibOAiAYvwdsa84nUmq6Pn5yPaWKWWLwk9JxXz5rN1gh-BC5Yg%3D%3D&sig=AOq0QJ8wRQIhAKvcs-TdR3qeO0Qbjp7r9H5VuEB6gBvoRZ4TFXa5gb7SAiAV8PY_5jOYLWza0JkFC8uIXzFYTabVK3QnE832yWZ69w==", "width": 1080, "ext": "mp4", "vcodec": "avc1.640020", "acodec": "none", "vbr": 241.479, "downloader_options": {"http_chunk_size": 10485760}, "container": "mp4_dash", "format": "137 - 1080x1080 (1080p)", "protocol": "https", "http_headers": {"User-Agent": "Mozilla/5.0 (Windows NT 10.0; Win64; x64) AppleWebKit/537.36 (KHTML, like Gecko) Chrome/69.0.3497.124 Safari/537.36", "Accept-Charset": "ISO-8859-1,utf-8;q=0.7,*;q=0.7", "Accept": "text/html,application/xhtml+xml,application/xml;q=0.9,*/*;q=0.8", "Accept-Encoding": "gzip, deflate", "Accept-Language": "en-us,en;q=0.5"}}, {"asr": null, "filesize": 19779383, "format_id": "248", "format_note": "1080p", "fps": 25, "height": 1080, "quality": 5, "tbr": 469.986, "url": "https://rr5---sn-0opoxu-ihvr.googlevideo.com/videoplayback?expire=1670741341&ei=_SiVY_AZz4WSBsjlpOAL&ip=189.173.225.87&id=o-ALa5WPpq7c-P_Vg3e1gjJ6dLt9ajSiAMlpktUFlus7RO&itag=248&aitags=133%2C134%2C135%2C136%2C137%2C160%2C242%2C243%2C244%2C247%2C248%2C278&source=youtube&requiressl=yes&mh=or&mm=31%2C29&mn=sn-0opoxu-ihvr%2Csn-q4fl6nsr&ms=au%2Crdu&mv=m&mvi=5&pcm2cms=yes&pl=24&gcr=mx&initcwndbps=790000&vprv=1&mime=video%2Fwebm&ns=vNF8sqv81lslM9vJtgRdEJAJ&gir=yes&clen=19779383&dur=336.680&lmt=1565912537969722&mt=1670719029&fvip=3&keepalive=yes&fexp=24001373%2C24007246&beids=24239132&c=WEB&txp=1311222&n=NnA-f9Fy3wBIFe1iM&sparams=expire%2Cei%2Cip%2Cid%2Caitags%2Csource%2Crequiressl%2Cgcr%2Cvprv%2Cmime%2Cns%2Cgir%2Cclen%2Cdur%2Clmt&lsparams=mh%2Cmm%2Cmn%2Cms%2Cmv%2Cmvi%2Cpcm2cms%2Cpl%2Cinitcwndbps&lsig=AG3C_xAwRQIhAM4uZaF16nW4tzSkzEuvgOJXqqod4iDwIdULQkXmjpJoAiBfck_jntu5b4m26lysNOrJHAiVVtVqWKzKaAERlbH4BA%3D%3D&sig=AOq0QJ8wRQIhANv90NOylSelqn4Y0UvbZEPj9g6SbOOzedHf6QiZg6R7AiAJie-9qvreYKci2pNXL84CyZDaSbds1iee8NYVmicIvQ==", "width": 1080, "ext": "webm", "vcodec": "vp9", "acodec": "none", "vbr": 469.986, "downloader_options": {"http_chunk_size": 10485760}, "container": "webm_dash", "format": "248 - 1080x1080 (1080p)", "protocol": "https", "http_headers": {"User-Agent": "Mozilla/5.0 (Windows NT 10.0; Win64; x64) AppleWebKit/537.36 (KHTML, like Gecko) Chrome/69.0.3497.124 Safari/537.36", "Accept-Charset": "ISO-8859-1,utf-8;q=0.7,*;q=0.7", "Accept": "text/html,application/xhtml+xml,application/xml;q=0.9,*/*;q=0.8", "Accept-Encoding": "gzip, deflate", "Accept-Language": "en-us,en;q=0.5"}}, {"asr": 22050, "filesize": null, "format_id": "18", "format_note": "360p", "fps": 25, "height": 360, "quality": 2, "tbr": 84.731, "url": "https://rr5---sn-0opoxu-ihvr.googlevideo.com/videoplayback?expire=1670741341&ei=_SiVY_AZz4WSBsjlpOAL&ip=189.173.225.87&id=o-ALa5WPpq7c-P_Vg3e1gjJ6dLt9ajSiAMlpktUFlus7RO&itag=18&source=youtube&requiressl=yes&mh=or&mm=31%2C29&mn=sn-0opoxu-ihvr%2Csn-q4fl6nsr&ms=au%2Crdu&mv=m&mvi=5&pcm2cms=yes&pl=24&gcr=mx&initcwndbps=790000&vprv=1&xtags=heaudio%3Dtrue&mime=video%2Fmp4&ns=mw17xVCzhFo_paa1Zef02E4J&cnr=14&ratebypass=yes&dur=336.811&lmt=1658651984444560&mt=1670719029&fvip=3&fexp=24001373%2C24007246&beids=24239132&c=WEB&txp=1318224&n=Gv22nr4iJIZXausY8&sparams=expire%2Cei%2Cip%2Cid%2Citag%2Csource%2Crequiressl%2Cgcr%2Cvprv%2Cxtags%2Cmime%2Cns%2Ccnr%2Cratebypass%2Cdur%2Clmt&lsparams=mh%2Cmm%2Cmn%2Cms%2Cmv%2Cmvi%2Cpcm2cms%2Cpl%2Cinitcwndbps&lsig=AG3C_xAwRgIhAILm8QfdhWrs4j-pF066WQvKaJcJeypiTf6POIDKkyM9AiEAh5Z0ncvZbRvaGwsW3tmBdto7hpyczRvmLEGpklSiz3E%3D&sig=AOq0QJ8wRQIhAN-_6qZNJyWMvs1uvK_y18tHDtDCAVAJqf1jt1O9R14ZAiBmguLf8lLHT3O3fjfZsNuupPGZFIl_F7CpZKqjDTJG3A==", "width": 360, "ext": "mp4", "vcodec": "avc1.42001E", "acodec": "mp4a.40.2", "format": "18 - 360x360 (360p)", "protocol": "https", "http_headers": {"User-Agent": "Mozilla/5.0 (Windows NT 10.0; Win64; x64) AppleWebKit/537.36 (KHTML, like Gecko) Chrome/69.0.3497.124 Safari/537.36", "Accept-Charset": "ISO-8859-1,utf-8;q=0.7,*;q=0.7", "Accept": "text/html,application/xhtml+xml,application/xml;q=0.9,*/*;q=0.8", "Accept-Encoding": "gzip, deflate", "Accept-Language": "en-us,en;q=0.5"}}], "thumbnails": [{"height": 94, "url": "https://i.ytimg.com/vi/0h7jEUbD9K8/hqdefault.jpg?sqp=-oaymwEbCKgBEF5IVfKriqkDDggBFQAAiEIYAXABwAEG&rs=AOn4CLBm53_ZWIu20rcp9p-owmHGhBk14w", "width": 168, "resolution": "168x94", "id": "0"}, {"height": 110, "url": "https://i.ytimg.com/vi/0h7jEUbD9K8/hqdefault.jpg?sqp=-oaymwEbCMQBEG5IVfKriqkDDggBFQAAiEIYAXABwAEG&rs=AOn4CLCor0I2mAm9TjZ12HDnYF23vPAG4w", "width": 196, "resolution": "196x110", "id": "1"}, {"height": 138, "url": "https://i.ytimg.com/vi/0h7jEUbD9K8/hqdefault.jpg?sqp=-oaymwEcCPYBEIoBSFXyq4qpAw4IARUAAIhCGAFwAcABBg==&rs=AOn4CLCAt8VnRU1XFkLCRSk2uHoY7m3H-g", "width": 246, "resolution": "246x138", "id": "2"}, {"height": 188, "url": "https://i.ytimg.com/vi/0h7jEUbD9K8/hqdefault.jpg?sqp=-oaymwEcCNACELwBSFXyq4qpAw4IARUAAIhCGAFwAcABBg==&rs=AOn4CLDT15H0-8pp0PwQHRi9yION1tz--Q", "width": 336, "resolution": "336x188", "id": "3"}, {"height": 1080, "url": "https://i.ytimg.com/vi_webp/0h7jEUbD9K8/maxresdefault.webp", "width": 1920, "resolution": "1920x1080", "id": "4"}], "description": "Provided to YouTube by Universal Music Group\n\nPonta De Areia \u00b7 Esperanza Spalding\n\nEsperanza\n\n\u2117 2008 Heads Up International\n\nReleased on: 2008-01-01\n\nProducer, Associated  Performer, Bass  Guitar, Vocals: Esperanza Spalding\nProducer, Co- Producer: Martin Walters\nAssociated  Performer, Background  Vocalist: Gretchen Parlato\nAssociated  Performer, Drums: Otis Brown\nAssociated  Performer, Percussion: Jamey Haddad\nAssociated  Performer, Piano: Leo Genovese\nComposer  Lyricist: Milton Nascimento\nComposer  Lyricist: Fernando Brant\n\nAuto-generated by YouTube.", "upload_date": "20180724", "uploader": "Esperanza Spalding - Topic", "uploader_id": "UCHI5oe34qE5XHR6-Asywspg", "uploader_url": "http://www.youtube.com/channel/UCHI5oe34qE5XHR6-Asywspg", "channel_id": "UCHI5oe34qE5XHR6-Asywspg", "channel_url": "https://www.youtube.com/channel/UCHI5oe34qE5XHR6-Asywspg", "duration": 337, "view_count": 194725, "average_rating": null, "age_limit": 0, "webpage_url": "https://www.youtube.com/watch?v=0h7jEUbD9K8", "categories": ["Music"], "tags": ["Esperanza Spalding", "\u30a8\u30b9\u30da\u30e9\u30f3\u30b5", "Esperanza", "Ponta De Areia", "\u30dd\u30f3\u30bf\u30c7\u30a2\u30ec\u30a4\u30a2", "\u30dd\u30f3\u30bf\u30fb\u30b8\u30fb\u30a2\u30ec\u30a4\u30a2"], "is_live": null, "album": "Esperanza", "artist": "Esperanza Spalding", "track": "Ponta De Areia", "release_date": "20080101", "release_year": 2008, "channel": "Esperanza Spalding", "creator": "Esperanza Spalding", "alt_title": "Ponta De Areia", "extractor": "youtube", "webpage_url_basename": "watch", "extractor_key": "Youtube", "playlist": null, "playlist_index": null, "thumbnail": "https://i.ytimg.com/vi_webp/0h7jEUbD9K8/maxresdefault.webp", "display_id": "0h7jEUbD9K8", "asr": 22050, "filesize": null, "format_id": "18", "format_note": "360p", "fps": 25, "height": 360, "quality": 2, "tbr": 84.731, "url": "https://rr5---sn-0opoxu-ihvr.googlevideo.com/videoplayback?expire=1670741341&ei=_SiVY_AZz4WSBsjlpOAL&ip=189.173.225.87&id=o-ALa5WPpq7c-P_Vg3e1gjJ6dLt9ajSiAMlpktUFlus7RO&itag=18&source=youtube&requiressl=yes&mh=or&mm=31%2C29&mn=sn-0opoxu-ihvr%2Csn-q4fl6nsr&ms=au%2Crdu&mv=m&mvi=5&pcm2cms=yes&pl=24&gcr=mx&initcwndbps=790000&vprv=1&xtags=heaudio%3Dtrue&mime=video%2Fmp4&ns=mw17xVCzhFo_paa1Zef02E4J&cnr=14&ratebypass=yes&dur=336.811&lmt=1658651984444560&mt=1670719029&fvip=3&fexp=24001373%2C24007246&beids=24239132&c=WEB&txp=1318224&n=Gv22nr4iJIZXausY8&sparams=expire%2Cei%2Cip%2Cid%2Citag%2Csource%2Crequiressl%2Cgcr%2Cvprv%2Cxtags%2Cmime%2Cns%2Ccnr%2Cratebypass%2Cdur%2Clmt&lsparams=mh%2Cmm%2Cmn%2Cms%2Cmv%2Cmvi%2Cpcm2cms%2Cpl%2Cinitcwndbps&lsig=AG3C_xAwRgIhAILm8QfdhWrs4j-pF066WQvKaJcJeypiTf6POIDKkyM9AiEAh5Z0ncvZbRvaGwsW3tmBdto7hpyczRvmLEGpklSiz3E%3D&sig=AOq0QJ8wRQIhAN-_6qZNJyWMvs1uvK_y18tHDtDCAVAJqf1jt1O9R14ZAiBmguLf8lLHT3O3fjfZsNuupPGZFIl_F7CpZKqjDTJG3A==", "width": 360, "ext": "mp4", "vcodec": "avc1.42001E", "acodec": "mp4a.40.2", "format": "18 - 360x360 (360p)", "protocol": "https", "http_headers": {"User-Agent": "Mozilla/5.0 (Windows NT 10.0; Win64; x64) AppleWebKit/537.36 (KHTML, like Gecko) Chrome/69.0.3497.124 Safari/537.36", "Accept-Charset": "ISO-8859-1,utf-8;q=0.7,*;q=0.7", "Accept": "text/html,application/xhtml+xml,application/xml;q=0.9,*/*;q=0.8", "Accept-Encoding": "gzip, deflate", "Accept-Language": "en-us,en;q=0.5"}, "fulltitle": "Ponta De Areia", "_filename": "Ponta De Areia-0h7jEUbD9K8.mp4"}